diapasons/__init__.py
diapasons/base.py
diapasons/exceptions.py
diapasons/tests.py
diapasons/validators.py
diapasons-0.0.3.dist-info/LICENSE
diapasons-0.0.3.dist-info/METADATA
diapasons-0.0.3.dist-info/WHEEL
diapasons-0.0.3.dist-info/top_level.txt
diapasons-0.0.3.dist-info/RECORD
