Metadata-Version: 2.1
Name: diapasons
Version: 0.0.3
Summary: simple library for working with data that can be represented as a set of points on a straight line.
Home-page: https://github.com/AlbertSabirzianov/diapasons
Author: a.sabirzianov
Author-email: albertuno@mail.com
Project-URL: GitHub, https://github.com/AlbertSabirzianov/diapasons
Keywords: diapasons sections lines points
Classifier: Programming Language :: Python :: 3.12
Classifier: License :: OSI Approved :: MIT License
Classifier: Operating System :: OS Independent
Requires-Python: >=3.6
License-File: LICENSE
Requires-Dist: pydantic >=2.6
